tofimaging/Data.py
tofimaging/EdgeFitting.py
tofimaging/FOBI_analysis.py
tofimaging/PhaseFitting.py
tofimaging/ReductionTools.py
tofimaging/__init__.py
tofimaging-1.0.1.dist-info/LICENSE
tofimaging-1.0.1.dist-info/METADATA
tofimaging-1.0.1.dist-info/WHEEL
tofimaging-1.0.1.dist-info/top_level.txt
tofimaging-1.0.1.dist-info/RECORD
