Metadata-Version: 2.1
Name: tofimaging
Version: 1.0.1
Summary: Library for neutron ToF imaging
Home-page: https://github.com/neutronimaging/ToFImaging
Author: Matteo Busi
Author-email: mbusi2691@gmail.com
License: UNKNOWN
Project-URL: Bug Tracker, https://github.com/neutronimaging/ToFImaging/issues
Platform: UNKNOWN
Classifier: Programming Language :: Python :: 3
Classifier: License :: OSI Approved :: MIT License
Classifier: Operating System :: OS Independent
Requires-Python: >=3.6
Requires-Dist: astropy
Requires-Dist: lmfit
Requires-Dist: matplotlib
Requires-Dist: numpy
Requires-Dist: scikit-image
Requires-Dist: scipy
Requires-Dist: tqdm
